messageanalyzer/__init__.py
messageanalyzer/detect_language_patterns.py
messageanalyzer/extract_keywords.py
messageanalyzer/sentiment_analysis.py
messageanalyzer/topic_modeling.py
messageanalyzer-2.0.3.dist-info/LICENSE
messageanalyzer-2.0.3.dist-info/METADATA
messageanalyzer-2.0.3.dist-info/WHEEL
messageanalyzer-2.0.3.dist-info/RECORD
