Metadata-Version: 2.3
Name: messageanalyzer
Version: 2.0.3
Summary: This package includes powerful tools to perform natural language processing on English texts.
License: MIT
Author: Quanhua Huang, Adrian Leung, Anna Nandar, Colombe Tolokin
Requires-Python: >=3.9,<4.0
Classifier: License :: OSI Approved :: MIT License
Classifier: Programming Language :: Python :: 3
Classifier: Programming Language :: Python :: 3.9
Classifier: Programming Language :: Python :: 3.10
Classifier: Programming Language :: Python :: 3.11
Classifier: Programming Language :: Python :: 3.12
Classifier: Programming Language :: Python :: 3.13
Requires-Dist: langdetect (>=1.0.9,<2.0.0)
Requires-Dist: matplotlib (>=3.9,<4.0)
Requires-Dist: pandas (>=2.2.3,<3.0.0)
Requires-Dist: scikit-learn (>=1.6.1,<2.0.0)
Requires-Dist: textblob (>=0.18.0.post0,<0.19.0)
